inputparser/__init__.py
inputparser/inputparser.py
inputparser/validators.py
UserInputParser-0.1.0.dist-info/LICENSE
UserInputParser-0.1.0.dist-info/METADATA
UserInputParser-0.1.0.dist-info/WHEEL
UserInputParser-0.1.0.dist-info/top_level.txt
UserInputParser-0.1.0.dist-info/RECORD
