Metadata-Version: 2.1
Name: UserInputParser
Version: 0.1.0
Summary: Parse user input to ensure it meets the specified constraints
Home-page: https://github.com/jkalish14/UserInputParser
Author: Jake Kalish
Author-email: jkalish14@gmail.com
License: MIT
Keywords: Parser,User,Input
Platform: UNKNOWN
License-File: LICENSE
